backports/pathlib/__init__.py
backports/pathlib/_tests.py
backports_pathlib_relative_to-0.1.0.dist-info/METADATA
backports_pathlib_relative_to-0.1.0.dist-info/WHEEL
backports_pathlib_relative_to-0.1.0.dist-info/RECORD
